[
    {
        "epoch": 1,
        "loss": 3.007499933242798,
        "best_loss": 3.007499933242798,
        "best_kl": 2.1449999809265137,
        "best_std": 0.2508364677429199,
        "cur_kl": 2.1449999809265137,
        "cur_std": 0.2508364677429199,
        "orig_prompt": {
            "text": "The day before two days after the day before tomorrow is Saturday. What day is it today?",
            "ids": [
                510,
                1388,
                1078,
                767,
                1897,
                846,
                253,
                1388,
                1078,
                10873,
                310,
                7814,
                15,
                1737,
                1388,
                310,
                352,
                3063,
                32
            ],
            "prompt_start_slice": 0,
            "prompt_end_slice": 19,
            "doc_start_slice": 19,
            "doc_end_slice": 51
        },
        "optim_prompt": {
            "text": " D the day before two days after the day before tomorrow is Saturday. Can you tell me what day is today?",
            "ids": [
                399,
                253,
                1388,
                1078,
                767,
                1897,
                846,
                253,
                1388,
                1078,
                10873,
                310,
                7814,
                15,
                2615,
                368,
                2028,
                479,
                752,
                1388,
                310,
                3063,
                32
            ],
            "prompt_start_slice": 0,
            "prompt_end_slice": 23,
            "doc_start_slice": 23,
            "doc_end_slice": 55
        },
        "nll_prompt": -72.0
    },
    {
        "epoch": 2,
        "loss": 2.9887499809265137,
        "best_loss": 2.9887499809265137,
        "best_kl": 1.8849999904632568,
        "best_std": 0.23694233894348143,
        "cur_kl": 1.8849999904632568,
        "cur_std": 0.23694233894348143,
        "orig_prompt": {
            "text": "The day before two days after the day before tomorrow is Saturday. What day is it today?",
            "ids": [
                510,
                1388,
                1078,
                767,
                1897,
                846,
                253,
                1388,
                1078,
                10873,
                310,
                7814,
                15,
                1737,
                1388,
                310,
                352,
                3063,
                32
            ],
            "prompt_start_slice": 0,
            "prompt_end_slice": 19,
            "doc_start_slice": 19,
            "doc_end_slice": 51
        },
        "optim_prompt": {
            "text": "ped the day before two days after the day before tomorrow is Saturday. Can you tell me what day is today?",
            "ids": [
                9357,
                253,
                1388,
                1078,
                767,
                1897,
                846,
                253,
                1388,
                1078,
                10873,
                310,
                7814,
                15,
                2615,
                368,
                2028,
                479,
                752,
                1388,
                310,
                3063,
                32
            ],
            "prompt_start_slice": 0,
            "prompt_end_slice": 23,
            "doc_start_slice": 23,
            "doc_end_slice": 55
        },
        "nll_prompt": -72.0
    },
    {
        "epoch": 3,
        "loss": 2.9962499141693115,
        "best_loss": 2.9887499809265137,
        "best_kl": 1.8849999904632568,
        "best_std": 0.23694233894348143,
        "cur_kl": 1.8874999284744263,
        "cur_std": 0.23842854499816896,
        "orig_prompt": {
            "text": "The day before two days after the day before tomorrow is Saturday. What day is it today?",
            "ids": [
                510,
                1388,
                1078,
                767,
                1897,
                846,
                253,
                1388,
                1078,
                10873,
                310,
                7814,
                15,
                1737,
                1388,
                310,
                352,
                3063,
                32
            ],
            "prompt_start_slice": 0,
            "prompt_end_slice": 19,
            "doc_start_slice": 19,
            "doc_end_slice": 51
        },
        "optim_prompt": {
            "text": "ify the day before two days after the day before tomorrow is Saturday. Can you tell me what day is today?",
            "ids": [
                1419,
                253,
                1388,
                1078,
                767,
                1897,
                846,
                253,
                1388,
                1078,
                10873,
                310,
                7814,
                15,
                2615,
                368,
                2028,
                479,
                752,
                1388,
                310,
                3063,
                32
            ],
            "prompt_start_slice": 0,
            "prompt_end_slice": 23,
            "doc_start_slice": 23,
            "doc_end_slice": 55
        },
        "nll_prompt": -66.5
    },
    {
        "epoch": 4,
        "loss": 2.9912500381469727,
        "best_loss": 2.9887499809265137,
        "best_kl": 1.8549998998641968,
        "best_std": 0.2490177869796753,
        "cur_kl": 1.8549998998641968,
        "cur_std": 0.2490177869796753,
        "orig_prompt": {
            "text": "The day before two days after the day before tomorrow is Saturday. What day is it today?",
            "ids": [
                510,
                1388,
                1078,
                767,
                1897,
                846,
                253,
                1388,
                1078,
                10873,
                310,
                7814,
                15,
                1737,
                1388,
                310,
                352,
                3063,
                32
            ],
            "prompt_start_slice": 0,
            "prompt_end_slice": 19,
            "doc_start_slice": 19,
            "doc_end_slice": 51
        },
        "optim_prompt": {
            "text": "ch the day before two days after the day before tomorrow is Saturday. Can you tell me what day is today?",
            "ids": [
                348,
                253,
                1388,
                1078,
                767,
                1897,
                846,
                253,
                1388,
                1078,
                10873,
                310,
                7814,
                15,
                2615,
                368,
                2028,
                479,
                752,
                1388,
                310,
                3063,
                32
            ],
            "prompt_start_slice": 0,
            "prompt_end_slice": 23,
            "doc_start_slice": 23,
            "doc_end_slice": 55
        },
        "nll_prompt": -71.0
    },
    {
        "epoch": 5,
        "loss": 2.9912500381469727,
        "best_loss": 2.9887499809265137,
        "best_kl": 1.7999999523162842,
        "best_std": 0.233819842338562,
        "cur_kl": 1.7999999523162842,
        "cur_std": 0.233819842338562,
        "orig_prompt": {
            "text": "The day before two days after the day before tomorrow is Saturday. What day is it today?",
            "ids": [
                510,
                1388,
                1078,
                767,
                1897,
                846,
                253,
                1388,
                1078,
                10873,
                310,
                7814,
                15,
                1737,
                1388,
                310,
                352,
                3063,
                32
            ],
            "prompt_start_slice": 0,
            "prompt_end_slice": 19,
            "doc_start_slice": 19,
            "doc_end_slice": 51
        },
        "optim_prompt": {
            "text": " there the day before two days after the day before tomorrow is Saturday. Can you tell me what day is today?",
            "ids": [
                627,
                253,
                1388,
                1078,
                767,
                1897,
                846,
                253,
                1388,
                1078,
                10873,
                310,
                7814,
                15,
                2615,
                368,
                2028,
                479,
                752,
                1388,
                310,
                3063,
                32
            ],
            "prompt_start_slice": 0,
            "prompt_end_slice": 23,
            "doc_start_slice": 23,
            "doc_end_slice": 55
        },
        "nll_prompt": -67.0
    },
    {
        "epoch": 6,
        "loss": 2.9887499809265137,
        "best_loss": 2.9887499809265137,
        "best_kl": 1.7999999523162842,
        "best_std": 0.233819842338562,
        "cur_kl": 1.9762499332427979,
        "cur_std": 0.21864404678344726,
        "orig_prompt": {
            "text": "The day before two days after the day before tomorrow is Saturday. What day is it today?",
            "ids": [
                510,
                1388,
                1078,
                767,
                1897,
                846,
                253,
                1388,
                1078,
                10873,
                310,
                7814,
                15,
                1737,
                1388,
                310,
                352,
                3063,
                32
            ],
            "prompt_start_slice": 0,
            "prompt_end_slice": 19,
            "doc_start_slice": 19,
            "doc_end_slice": 51
        },
        "optim_prompt": {
            "text": " there the day before two days after the day before tomorrow is Saturday. Can you tell, what day is today?",
            "ids": [
                627,
                253,
                1388,
                1078,
                767,
                1897,
                846,
                253,
                1388,
                1078,
                10873,
                310,
                7814,
                15,
                2615,
                368,
                2028,
                13,
                752,
                1388,
                310,
                3063,
                32
            ],
            "prompt_start_slice": 0,
            "prompt_end_slice": 23,
            "doc_start_slice": 23,
            "doc_end_slice": 55
        },
        "nll_prompt": -75.5
    },
    {
        "epoch": 7,
        "loss": 2.9987499713897705,
        "best_loss": 2.9887499809265137,
        "best_kl": 1.7999999523162842,
        "best_std": 0.233819842338562,
        "cur_kl": 2.317499876022339,
        "cur_std": 0.23700718879699706,
        "orig_prompt": {
            "text": "The day before two days after the day before tomorrow is Saturday. What day is it today?",
            "ids": [
                510,
                1388,
                1078,
                767,
                1897,
                846,
                253,
                1388,
                1078,
                10873,
                310,
                7814,
                15,
                1737,
                1388,
                310,
                352,
                3063,
                32
            ],
            "prompt_start_slice": 0,
            "prompt_end_slice": 19,
            "doc_start_slice": 19,
            "doc_end_slice": 51
        },
        "optim_prompt": {
            "text": "woman the day before two days after the day before tomorrow is Saturday. Can you tell, what day is today?",
            "ids": [
                17217,
                253,
                1388,
                1078,
                767,
                1897,
                846,
                253,
                1388,
                1078,
                10873,
                310,
                7814,
                15,
                2615,
                368,
                2028,
                13,
                752,
                1388,
                310,
                3063,
                32
            ],
            "prompt_start_slice": 0,
            "prompt_end_slice": 23,
            "doc_start_slice": 23,
            "doc_end_slice": 55
        },
        "nll_prompt": -80.0
    },
    {
        "epoch": 8,
        "loss": 3.0087499618530273,
        "best_loss": 2.9887499809265137,
        "best_kl": 1.7999999523162842,
        "best_std": 0.233819842338562,
        "cur_kl": 2.384999990463257,
        "cur_std": 0.24846549034118653,
        "orig_prompt": {
            "text": "The day before two days after the day before tomorrow is Saturday. What day is it today?",
            "ids": [
                510,
                1388,
                1078,
                767,
                1897,
                846,
                253,
                1388,
                1078,
                10873,
                310,
                7814,
                15,
                1737,
                1388,
                310,
                352,
                3063,
                32
            ],
            "prompt_start_slice": 0,
            "prompt_end_slice": 19,
            "doc_start_slice": 19,
            "doc_end_slice": 51
        },
        "optim_prompt": {
            "text": " 1 the day before two days after the day before tomorrow is Saturday. Can you tell, what day is today?",
            "ids": [
                337,
                253,
                1388,
                1078,
                767,
                1897,
                846,
                253,
                1388,
                1078,
                10873,
                310,
                7814,
                15,
                2615,
                368,
                2028,
                13,
                752,
                1388,
                310,
                3063,
                32
            ],
            "prompt_start_slice": 0,
            "prompt_end_slice": 23,
            "doc_start_slice": 23,
            "doc_end_slice": 55
        },
        "nll_prompt": -80.0
    },
    {
        "epoch": 9,
        "loss": 3.0,
        "best_loss": 2.9887499809265137,
        "best_kl": 1.7999999523162842,
        "best_std": 0.233819842338562,
        "cur_kl": 2.357499837875366,
        "cur_std": 0.23648455142974853,
        "orig_prompt": {
            "text": "The day before two days after the day before tomorrow is Saturday. What day is it today?",
            "ids": [
                510,
                1388,
                1078,
                767,
                1897,
                846,
                253,
                1388,
                1078,
                10873,
                310,
                7814,
                15,
                1737,
                1388,
                310,
                352,
                3063,
                32
            ],
            "prompt_start_slice": 0,
            "prompt_end_slice": 19,
            "doc_start_slice": 19,
            "doc_end_slice": 51
        },
        "optim_prompt": {
            "text": "athom the day before two days after the day before tomorrow is Saturday. Can you tell, what day is today?",
            "ids": [
                50092,
                253,
                1388,
                1078,
                767,
                1897,
                846,
                253,
                1388,
                1078,
                10873,
                310,
                7814,
                15,
                2615,
                368,
                2028,
                13,
                752,
                1388,
                310,
                3063,
                32
            ],
            "prompt_start_slice": 0,
            "prompt_end_slice": 23,
            "doc_start_slice": 23,
            "doc_end_slice": 55
        },
        "nll_prompt": -77.0
    },
    {
        "epoch": 10,
        "loss": 2.997499942779541,
        "best_loss": 2.9887499809265137,
        "best_kl": 1.7999999523162842,
        "best_std": 0.233819842338562,
        "cur_kl": 2.0249998569488525,
        "cur_std": 0.24892444610595704,
        "orig_prompt": {
            "text": "The day before two days after the day before tomorrow is Saturday. What day is it today?",
            "ids": [
                510,
                1388,
                1078,
                767,
                1897,
                846,
                253,
                1388,
                1078,
                10873,
                310,
                7814,
                15,
                1737,
                1388,
                310,
                352,
                3063,
                32
            ],
            "prompt_start_slice": 0,
            "prompt_end_slice": 19,
            "doc_start_slice": 19,
            "doc_end_slice": 51
        },
        "optim_prompt": {
            "text": "Of the day before two days after the day before tomorrow is Saturday. Can you tell, what day is today?",
            "ids": [
                4527,
                253,
                1388,
                1078,
                767,
                1897,
                846,
                253,
                1388,
                1078,
                10873,
                310,
                7814,
                15,
                2615,
                368,
                2028,
                13,
                752,
                1388,
                310,
                3063,
                32
            ],
            "prompt_start_slice": 0,
            "prompt_end_slice": 23,
            "doc_start_slice": 23,
            "doc_end_slice": 55
        },
        "nll_prompt": -81.0
    },
    {
        "epoch": 11,
        "loss": 2.9937498569488525,
        "best_loss": 2.9887499809265137,
        "best_kl": 1.7999999523162842,
        "best_std": 0.233819842338562,
        "cur_kl": 2.3162498474121094,
        "cur_std": 0.24038619995117189,
        "orig_prompt": {
            "text": "The day before two days after the day before tomorrow is Saturday. What day is it today?",
            "ids": [
                510,
                1388,
                1078,
                767,
                1897,
                846,
                253,
                1388,
                1078,
                10873,
                310,
                7814,
                15,
                1737,
                1388,
                310,
                352,
                3063,
                32
            ],
            "prompt_start_slice": 0,
            "prompt_end_slice": 19,
            "doc_start_slice": 19,
            "doc_end_slice": 51
        },
        "optim_prompt": {
            "text": " wait the day before two days after the day before tomorrow is Saturday. Can you tell, what day is today?",
            "ids": [
                3343,
                253,
                1388,
                1078,
                767,
                1897,
                846,
                253,
                1388,
                1078,
                10873,
                310,
                7814,
                15,
                2615,
                368,
                2028,
                13,
                752,
                1388,
                310,
                3063,
                32
            ],
            "prompt_start_slice": 0,
            "prompt_end_slice": 23,
            "doc_start_slice": 23,
            "doc_end_slice": 55
        },
        "nll_prompt": -76.0
    },
    {
        "epoch": 12,
        "loss": 2.994999885559082,
        "best_loss": 2.9887499809265137,
        "best_kl": 1.7999999523162842,
        "best_std": 0.233819842338562,
        "cur_kl": 1.9237499237060547,
        "cur_std": 0.22951347827911378,
        "orig_prompt": {
            "text": "The day before two days after the day before tomorrow is Saturday. What day is it today?",
            "ids": [
                510,
                1388,
                1078,
                767,
                1897,
                846,
                253,
                1388,
                1078,
                10873,
                310,
                7814,
                15,
                1737,
                1388,
                310,
                352,
                3063,
                32
            ],
            "prompt_start_slice": 0,
            "prompt_end_slice": 19,
            "doc_start_slice": 19,
            "doc_end_slice": 51
        },
        "optim_prompt": {
            "text": "he the day before two days after the day before tomorrow is Saturday. Can you tell, what day is today?",
            "ids": [
                248,
                253,
                1388,
                1078,
                767,
                1897,
                846,
                253,
                1388,
                1078,
                10873,
                310,
                7814,
                15,
                2615,
                368,
                2028,
                13,
                752,
                1388,
                310,
                3063,
                32
            ],
            "prompt_start_slice": 0,
            "prompt_end_slice": 23,
            "doc_start_slice": 23,
            "doc_end_slice": 55
        },
        "nll_prompt": -78.5
    },
    {
        "epoch": 13,
        "loss": 3.0087499618530273,
        "best_loss": 2.9887499809265137,
        "best_kl": 1.7999999523162842,
        "best_std": 0.233819842338562,
        "cur_kl": 2.3924999237060547,
        "cur_std": 0.24957680702209473,
        "orig_prompt": {
            "text": "The day before two days after the day before tomorrow is Saturday. What day is it today?",
            "ids": [
                510,
                1388,
                1078,
                767,
                1897,
                846,
                253,
                1388,
                1078,
                10873,
                310,
                7814,
                15,
                1737,
                1388,
                310,
                352,
                3063,
                32
            ],
            "prompt_start_slice": 0,
            "prompt_end_slice": 19,
            "doc_start_slice": 19,
            "doc_end_slice": 51
        },
        "optim_prompt": {
            "text": "he Clock day before two days after the day before tomorrow is Saturday. Can you tell, what day is today?",
            "ids": [
                248,
                41388,
                1388,
                1078,
                767,
                1897,
                846,
                253,
                1388,
                1078,
                10873,
                310,
                7814,
                15,
                2615,
                368,
                2028,
                13,
                752,
                1388,
                310,
                3063,
                32
            ],
            "prompt_start_slice": 0,
            "prompt_end_slice": 23,
            "doc_start_slice": 23,
            "doc_end_slice": 55
        },
        "nll_prompt": -93.0
    },
    {
        "epoch": 14,
        "loss": 3.013749837875366,
        "best_loss": 2.9887499809265137,
        "best_kl": 1.7999999523162842,
        "best_std": 0.233819842338562,
        "cur_kl": 2.391249895095825,
        "cur_std": 0.25409932136535646,
        "orig_prompt": {
            "text": "The day before two days after the day before tomorrow is Saturday. What day is it today?",
            "ids": [
                510,
                1388,
                1078,
                767,
                1897,
                846,
                253,
                1388,
                1078,
                10873,
                310,
                7814,
                15,
                1737,
                1388,
                310,
                352,
                3063,
                32
            ],
            "prompt_start_slice": 0,
            "prompt_end_slice": 19,
            "doc_start_slice": 19,
            "doc_end_slice": 51
        },
        "optim_prompt": {
            "text": "he hard day before two days after the day before tomorrow is Saturday. Can you tell, what day is today?",
            "ids": [
                248,
                1892,
                1388,
                1078,
                767,
                1897,
                846,
                253,
                1388,
                1078,
                10873,
                310,
                7814,
                15,
                2615,
                368,
                2028,
                13,
                752,
                1388,
                310,
                3063,
                32
            ],
            "prompt_start_slice": 0,
            "prompt_end_slice": 23,
            "doc_start_slice": 23,
            "doc_end_slice": 55
        },
        "nll_prompt": -93.5
    },
    {
        "epoch": 15,
        "loss": 3.00249981880188,
        "best_loss": 2.9887499809265137,
        "best_kl": 1.7999999523162842,
        "best_std": 0.233819842338562,
        "cur_kl": 2.1362500190734863,
        "cur_std": 0.2319704294204712,
        "orig_prompt": {
            "text": "The day before two days after the day before tomorrow is Saturday. What day is it today?",
            "ids": [
                510,
                1388,
                1078,
                767,
                1897,
                846,
                253,
                1388,
                1078,
                10873,
                310,
                7814,
                15,
                1737,
                1388,
                310,
                352,
                3063,
                32
            ],
            "prompt_start_slice": 0,
            "prompt_end_slice": 19,
            "doc_start_slice": 19,
            "doc_end_slice": 51
        },
        "optim_prompt": {
            "text": "heolar day before two days after the day before tomorrow is Saturday. Can you tell, what day is today?",
            "ids": [
                248,
                6062,
                1388,
                1078,
                767,
                1897,
                846,
                253,
                1388,
                1078,
                10873,
                310,
                7814,
                15,
                2615,
                368,
                2028,
                13,
                752,
                1388,
                310,
                3063,
                32
            ],
            "prompt_start_slice": 0,
            "prompt_end_slice": 23,
            "doc_start_slice": 23,
            "doc_end_slice": 55
        },
        "nll_prompt": -97.5
    },
    {
        "epoch": 16,
        "loss": 3.023749828338623,
        "best_loss": 2.9887499809265137,
        "best_kl": 1.7999999523162842,
        "best_std": 0.233819842338562,
        "cur_kl": 2.78374981880188,
        "cur_std": 0.2970757007598877,
        "orig_prompt": {
            "text": "The day before two days after the day before tomorrow is Saturday. What day is it today?",
            "ids": [
                510,
                1388,
                1078,
                767,
                1897,
                846,
                253,
                1388,
                1078,
                10873,
                310,
                7814,
                15,
                1737,
                1388,
                310,
                352,
                3063,
                32
            ],
            "prompt_start_slice": 0,
            "prompt_end_slice": 19,
            "doc_start_slice": 19,
            "doc_end_slice": 51
        },
        "optim_prompt": {
            "text": "heolar dayread two days after the day before tomorrow is Saturday. Can you tell, what day is today?",
            "ids": [
                248,
                6062,
                1388,
                1088,
                767,
                1897,
                846,
                253,
                1388,
                1078,
                10873,
                310,
                7814,
                15,
                2615,
                368,
                2028,
                13,
                752,
                1388,
                310,
                3063,
                32
            ],
            "prompt_start_slice": 0,
            "prompt_end_slice": 23,
            "doc_start_slice": 23,
            "doc_end_slice": 55
        },
        "nll_prompt": -106.5
    },
    {
        "epoch": 17,
        "loss": 3.021250009536743,
        "best_loss": 2.9887499809265137,
        "best_kl": 1.7999999523162842,
        "best_std": 0.233819842338562,
        "cur_kl": 2.75,
        "cur_std": 0.29633705615997313,
        "orig_prompt": {
            "text": "The day before two days after the day before tomorrow is Saturday. What day is it today?",
            "ids": [
                510,
                1388,
                1078,
                767,
                1897,
                846,
                253,
                1388,
                1078,
                10873,
                310,
                7814,
                15,
                1737,
                1388,
                310,
                352,
                3063,
                32
            ],
            "prompt_start_slice": 0,
            "prompt_end_slice": 19,
            "doc_start_slice": 19,
            "doc_end_slice": 51
        },
        "optim_prompt": {
            "text": "heolar day are two days after the day before tomorrow is Saturday. Can you tell, what day is today?",
            "ids": [
                248,
                6062,
                1388,
                403,
                767,
                1897,
                846,
                253,
                1388,
                1078,
                10873,
                310,
                7814,
                15,
                2615,
                368,
                2028,
                13,
                752,
                1388,
                310,
                3063,
                32
            ],
            "prompt_start_slice": 0,
            "prompt_end_slice": 23,
            "doc_start_slice": 23,
            "doc_end_slice": 55
        },
        "nll_prompt": -96.5
    },
    {
        "epoch": 18,
        "loss": 3.0174999237060547,
        "best_loss": 2.9887499809265137,
        "best_kl": 1.7999999523162842,
        "best_std": 0.233819842338562,
        "cur_kl": 2.78125,
        "cur_std": 0.2814743757247925,
        "orig_prompt": {
            "text": "The day before two days after the day before tomorrow is Saturday. What day is it today?",
            "ids": [
                510,
                1388,
                1078,
                767,
                1897,
                846,
                253,
                1388,
                1078,
                10873,
                310,
                7814,
                15,
                1737,
                1388,
                310,
                352,
                3063,
                32
            ],
            "prompt_start_slice": 0,
            "prompt_end_slice": 19,
            "doc_start_slice": 19,
            "doc_end_slice": 51
        },
        "optim_prompt": {
            "text": "heolar day day two days after the day before tomorrow is Saturday. Can you tell, what day is today?",
            "ids": [
                248,
                6062,
                1388,
                1388,
                767,
                1897,
                846,
                253,
                1388,
                1078,
                10873,
                310,
                7814,
                15,
                2615,
                368,
                2028,
                13,
                752,
                1388,
                310,
                3063,
                32
            ],
            "prompt_start_slice": 0,
            "prompt_end_slice": 23,
            "doc_start_slice": 23,
            "doc_end_slice": 55
        },
        "nll_prompt": -98.0
    },
    {
        "epoch": 19,
        "loss": 3.0199999809265137,
        "best_loss": 2.9887499809265137,
        "best_kl": 1.7999999523162842,
        "best_std": 0.233819842338562,
        "cur_kl": 2.7487499713897705,
        "cur_std": 0.29458763599395754,
        "orig_prompt": {
            "text": "The day before two days after the day before tomorrow is Saturday. What day is it today?",
            "ids": [
                510,
                1388,
                1078,
                767,
                1897,
                846,
                253,
                1388,
                1078,
                10873,
                310,
                7814,
                15,
                1737,
                1388,
                310,
                352,
                3063,
                32
            ],
            "prompt_start_slice": 0,
            "prompt_end_slice": 19,
            "doc_start_slice": 19,
            "doc_end_slice": 51
        },
        "optim_prompt": {
            "text": "heolarean day two days after the day before tomorrow is Saturday. Can you tell, what day is today?",
            "ids": [
                248,
                6062,
                15719,
                1388,
                767,
                1897,
                846,
                253,
                1388,
                1078,
                10873,
                310,
                7814,
                15,
                2615,
                368,
                2028,
                13,
                752,
                1388,
                310,
                3063,
                32
            ],
            "prompt_start_slice": 0,
            "prompt_end_slice": 23,
            "doc_start_slice": 23,
            "doc_end_slice": 55
        },
        "nll_prompt": -106.0
    },
    {
        "epoch": 20,
        "loss": 3.0174999237060547,
        "best_loss": 2.9887499809265137,
        "best_kl": 1.7999999523162842,
        "best_std": 0.233819842338562,
        "cur_kl": 2.4362499713897705,
        "cur_std": 0.28010358810424807,
        "orig_prompt": {
            "text": "The day before two days after the day before tomorrow is Saturday. What day is it today?",
            "ids": [
                510,
                1388,
                1078,
                767,
                1897,
                846,
                253,
                1388,
                1078,
                10873,
                310,
                7814,
                15,
                1737,
                1388,
                310,
                352,
                3063,
                32
            ],
            "prompt_start_slice": 0,
            "prompt_end_slice": 19,
            "doc_start_slice": 19,
            "doc_end_slice": 51
        },
        "optim_prompt": {
            "text": "heiclesean day two days after the day before tomorrow is Saturday. Can you tell, what day is today?",
            "ids": [
                248,
                3741,
                15719,
                1388,
                767,
                1897,
                846,
                253,
                1388,
                1078,
                10873,
                310,
                7814,
                15,
                2615,
                368,
                2028,
                13,
                752,
                1388,
                310,
                3063,
                32
            ],
            "prompt_start_slice": 0,
            "prompt_end_slice": 23,
            "doc_start_slice": 23,
            "doc_end_slice": 55
        },
        "nll_prompt": -107.0
    },
    {
        "epoch": 21,
        "loss": 3.038749933242798,
        "best_loss": 2.9887499809265137,
        "best_kl": 1.7999999523162842,
        "best_std": 0.233819842338562,
        "cur_kl": 3.581249952316284,
        "cur_std": 0.31353805065155027,
        "orig_prompt": {
            "text": "The day before two days after the day before tomorrow is Saturday. What day is it today?",
            "ids": [
                510,
                1388,
                1078,
                767,
                1897,
                846,
                253,
                1388,
                1078,
                10873,
                310,
                7814,
                15,
                1737,
                1388,
                310,
                352,
                3063,
                32
            ],
            "prompt_start_slice": 0,
            "prompt_end_slice": 19,
            "doc_start_slice": 19,
            "doc_end_slice": 51
        },
        "optim_prompt": {
            "text": "heJacean day two days after the day before tomorrow is Saturday. Can you tell, what day is today?",
            "ids": [
                248,
                26106,
                15719,
                1388,
                767,
                1897,
                846,
                253,
                1388,
                1078,
                10873,
                310,
                7814,
                15,
                2615,
                368,
                2028,
                13,
                752,
                1388,
                310,
                3063,
                32
            ],
            "prompt_start_slice": 0,
            "prompt_end_slice": 23,
            "doc_start_slice": 23,
            "doc_end_slice": 55
        },
        "nll_prompt": -104.5
    },
    {
        "epoch": 22,
        "loss": 3.023749828338623,
        "best_loss": 2.9887499809265137,
        "best_kl": 1.7999999523162842,
        "best_std": 0.233819842338562,
        "cur_kl": 2.851249933242798,
        "cur_std": 0.3016667366027832,
        "orig_prompt": {
            "text": "The day before two days after the day before tomorrow is Saturday. What day is it today?",
            "ids": [
                510,
                1388,
                1078,
                767,
                1897,
                846,
                253,
                1388,
                1078,
                10873,
                310,
                7814,
                15,
                1737,
                1388,
                310,
                352,
                3063,
                32
            ],
            "prompt_start_slice": 0,
            "prompt_end_slice": 19,
            "doc_start_slice": 19,
            "doc_end_slice": 51
        },
        "optim_prompt": {
            "text": "FROMJacean day two days after the day before tomorrow is Saturday. Can you tell, what day is today?",
            "ids": [
                22050,
                26106,
                15719,
                1388,
                767,
                1897,
                846,
                253,
                1388,
                1078,
                10873,
                310,
                7814,
                15,
                2615,
                368,
                2028,
                13,
                752,
                1388,
                310,
                3063,
                32
            ],
            "prompt_start_slice": 0,
            "prompt_end_slice": 23,
            "doc_start_slice": 23,
            "doc_end_slice": 55
        },
        "nll_prompt": -107.0
    },
    {
        "epoch": 23,
        "loss": 3.021250009536743,
        "best_loss": 2.9887499809265137,
        "best_kl": 1.7999999523162842,
        "best_std": 0.233819842338562,
        "cur_kl": 2.8862500190734863,
        "cur_std": 0.30439281463623047,
        "orig_prompt": {
            "text": "The day before two days after the day before tomorrow is Saturday. What day is it today?",
            "ids": [
                510,
                1388,
                1078,
                767,
                1897,
                846,
                253,
                1388,
                1078,
                10873,
                310,
                7814,
                15,
                1737,
                1388,
                310,
                352,
                3063,
                32
            ],
            "prompt_start_slice": 0,
            "prompt_end_slice": 19,
            "doc_start_slice": 19,
            "doc_end_slice": 51
        },
        "optim_prompt": {
            "text": "FROM1988ean day two days after the day before tomorrow is Saturday. Can you tell, what day is today?",
            "ids": [
                22050,
                14619,
                15719,
                1388,
                767,
                1897,
                846,
                253,
                1388,
                1078,
                10873,
                310,
                7814,
                15,
                2615,
                368,
                2028,
                13,
                752,
                1388,
                310,
                3063,
                32
            ],
            "prompt_start_slice": 0,
            "prompt_end_slice": 23,
            "doc_start_slice": 23,
            "doc_end_slice": 55
        },
        "nll_prompt": -112.0
    },
    {
        "epoch": 24,
        "loss": 3.021250009536743,
        "best_loss": 2.9887499809265137,
        "best_kl": 1.7999999523162842,
        "best_std": 0.233819842338562,
        "cur_kl": 2.78374981880188,
        "cur_std": 0.2997308254241943,
        "orig_prompt": {
            "text": "The day before two days after the day before tomorrow is Saturday. What day is it today?",
            "ids": [
                510,
                1388,
                1078,
                767,
                1897,
                846,
                253,
                1388,
                1078,
                10873,
                310,
                7814,
                15,
                1737,
                1388,
                310,
                352,
                3063,
                32
            ],
            "prompt_start_slice": 0,
            "prompt_end_slice": 19,
            "doc_start_slice": 19,
            "doc_end_slice": 51
        },
        "optim_prompt": {
            "text": "FROMopheean day two days after the day before tomorrow is Saturday. Can you tell, what day is today?",
            "ids": [
                22050,
                37245,
                15719,
                1388,
                767,
                1897,
                846,
                253,
                1388,
                1078,
                10873,
                310,
                7814,
                15,
                2615,
                368,
                2028,
                13,
                752,
                1388,
                310,
                3063,
                32
            ],
            "prompt_start_slice": 0,
            "prompt_end_slice": 23,
            "doc_start_slice": 23,
            "doc_end_slice": 55
        },
        "nll_prompt": -114.0
    },
    {
        "epoch": 25,
        "loss": 3.018749952316284,
        "best_loss": 2.9887499809265137,
        "best_kl": 1.7999999523162842,
        "best_std": 0.233819842338562,
        "cur_kl": 2.591249942779541,
        "cur_std": 0.28651211261749265,
        "orig_prompt": {
            "text": "The day before two days after the day before tomorrow is Saturday. What day is it today?",
            "ids": [
                510,
                1388,
                1078,
                767,
                1897,
                846,
                253,
                1388,
                1078,
                10873,
                310,
                7814,
                15,
                1737,
                1388,
                310,
                352,
                3063,
                32
            ],
            "prompt_start_slice": 0,
            "prompt_end_slice": 19,
            "doc_start_slice": 19,
            "doc_end_slice": 51
        },
        "optim_prompt": {
            "text": "FROMouean day two days after the day before tomorrow is Saturday. Can you tell, what day is today?",
            "ids": [
                22050,
                276,
                15719,
                1388,
                767,
                1897,
                846,
                253,
                1388,
                1078,
                10873,
                310,
                7814,
                15,
                2615,
                368,
                2028,
                13,
                752,
                1388,
                310,
                3063,
                32
            ],
            "prompt_start_slice": 0,
            "prompt_end_slice": 23,
            "doc_start_slice": 23,
            "doc_end_slice": 55
        },
        "nll_prompt": -112.0
    },
    {
        "epoch": 26,
        "loss": 3.013749837875366,
        "best_loss": 2.9887499809265137,
        "best_kl": 1.7999999523162842,
        "best_std": 0.233819842338562,
        "cur_kl": 2.586249828338623,
        "cur_std": 0.2748661994934082,
        "orig_prompt": {
            "text": "The day before two days after the day before tomorrow is Saturday. What day is it today?",
            "ids": [
                510,
                1388,
                1078,
                767,
                1897,
                846,
                253,
                1388,
                1078,
                10873,
                310,
                7814,
                15,
                1737,
                1388,
                310,
                352,
                3063,
                32
            ],
            "prompt_start_slice": 0,
            "prompt_end_slice": 19,
            "doc_start_slice": 19,
            "doc_end_slice": 51
        },
        "optim_prompt": {
            "text": "fromouean day two days after the day before tomorrow is Saturday. Can you tell, what day is today?",
            "ids": [
                4064,
                276,
                15719,
                1388,
                767,
                1897,
                846,
                253,
                1388,
                1078,
                10873,
                310,
                7814,
                15,
                2615,
                368,
                2028,
                13,
                752,
                1388,
                310,
                3063,
                32
            ],
            "prompt_start_slice": 0,
            "prompt_end_slice": 23,
            "doc_start_slice": 23,
            "doc_end_slice": 55
        },
        "nll_prompt": -108.0
    },
    {
        "epoch": 27,
        "loss": 3.009999990463257,
        "best_loss": 2.9887499809265137,
        "best_kl": 1.7999999523162842,
        "best_std": 0.233819842338562,
        "cur_kl": 2.326249837875366,
        "cur_std": 0.2809384822845459,
        "orig_prompt": {
            "text": "The day before two days after the day before tomorrow is Saturday. What day is it today?",
            "ids": [
                510,
                1388,
                1078,
                767,
                1897,
                846,
                253,
                1388,
                1078,
                10873,
                310,
                7814,
                15,
                1737,
                1388,
                310,
                352,
                3063,
                32
            ],
            "prompt_start_slice": 0,
            "prompt_end_slice": 19,
            "doc_start_slice": 19,
            "doc_end_slice": 51
        },
        "optim_prompt": {
            "text": "from particularlyean day two days after the day before tomorrow is Saturday. Can you tell, what day is today?",
            "ids": [
                4064,
                3782,
                15719,
                1388,
                767,
                1897,
                846,
                253,
                1388,
                1078,
                10873,
                310,
                7814,
                15,
                2615,
                368,
                2028,
                13,
                752,
                1388,
                310,
                3063,
                32
            ],
            "prompt_start_slice": 0,
            "prompt_end_slice": 23,
            "doc_start_slice": 23,
            "doc_end_slice": 55
        },
        "nll_prompt": -113.5
    },
    {
        "epoch": 28,
        "loss": 3.009999990463257,
        "best_loss": 2.9887499809265137,
        "best_kl": 1.7999999523162842,
        "best_std": 0.233819842338562,
        "cur_kl": 2.653749942779541,
        "cur_std": 0.2965226411819458,
        "orig_prompt": {
            "text": "The day before two days after the day before tomorrow is Saturday. What day is it today?",
            "ids": [
                510,
                1388,
                1078,
                767,
                1897,
                846,
                253,
                1388,
                1078,
                10873,
                310,
                7814,
                15,
                1737,
                1388,
                310,
                352,
                3063,
                32
            ],
            "prompt_start_slice": 0,
            "prompt_end_slice": 19,
            "doc_start_slice": 19,
            "doc_end_slice": 51
        },
        "optim_prompt": {
            "text": "from particularly fact day two days after the day before tomorrow is Saturday. Can you tell, what day is today?",
            "ids": [
                4064,
                3782,
                958,
                1388,
                767,
                1897,
                846,
                253,
                1388,
                1078,
                10873,
                310,
                7814,
                15,
                2615,
                368,
                2028,
                13,
                752,
                1388,
                310,
                3063,
                32
            ],
            "prompt_start_slice": 0,
            "prompt_end_slice": 23,
            "doc_start_slice": 23,
            "doc_end_slice": 55
        },
        "nll_prompt": -111.0
    },
    {
        "epoch": 29,
        "loss": 3.018749952316284,
        "best_loss": 2.9887499809265137,
        "best_kl": 1.7999999523162842,
        "best_std": 0.233819842338562,
        "cur_kl": 3.0737500190734863,
        "cur_std": 0.30007941722869874,
        "orig_prompt": {
            "text": "The day before two days after the day before tomorrow is Saturday. What day is it today?",
            "ids": [
                510,
                1388,
                1078,
                767,
                1897,
                846,
                253,
                1388,
                1078,
                10873,
                310,
                7814,
                15,
                1737,
                1388,
                310,
                352,
                3063,
                32
            ],
            "prompt_start_slice": 0,
            "prompt_end_slice": 19,
            "doc_start_slice": 19,
            "doc_end_slice": 51
        },
        "optim_prompt": {
            "text": "His particularly fact day two days after the day before tomorrow is Saturday. Can you tell, what day is today?",
            "ids": [
                8389,
                3782,
                958,
                1388,
                767,
                1897,
                846,
                253,
                1388,
                1078,
                10873,
                310,
                7814,
                15,
                2615,
                368,
                2028,
                13,
                752,
                1388,
                310,
                3063,
                32
            ],
            "prompt_start_slice": 0,
            "prompt_end_slice": 23,
            "doc_start_slice": 23,
            "doc_end_slice": 55
        },
        "nll_prompt": -107.5
    },
    {
        "epoch": 30,
        "loss": 3.028749942779541,
        "best_loss": 2.9887499809265137,
        "best_kl": 1.7999999523162842,
        "best_std": 0.233819842338562,
        "cur_kl": 3.1362500190734863,
        "cur_std": 0.2954468011856079,
        "orig_prompt": {
            "text": "The day before two days after the day before tomorrow is Saturday. What day is it today?",
            "ids": [
                510,
                1388,
                1078,
                767,
                1897,
                846,
                253,
                1388,
                1078,
                10873,
                310,
                7814,
                15,
                1737,
                1388,
                310,
                352,
                3063,
                32
            ],
            "prompt_start_slice": 0,
            "prompt_end_slice": 19,
            "doc_start_slice": 19,
            "doc_end_slice": 51
        },
        "optim_prompt": {
            "text": "offic particularly fact day two days after the day before tomorrow is Saturday. Can you tell, what day is today?",
            "ids": [
                19102,
                3782,
                958,
                1388,
                767,
                1897,
                846,
                253,
                1388,
                1078,
                10873,
                310,
                7814,
                15,
                2615,
                368,
                2028,
                13,
                752,
                1388,
                310,
                3063,
                32
            ],
            "prompt_start_slice": 0,
            "prompt_end_slice": 23,
            "doc_start_slice": 23,
            "doc_end_slice": 55
        },
        "nll_prompt": -108.5
    },
    {
        "epoch": 31,
        "loss": 3.0174999237060547,
        "best_loss": 2.9887499809265137,
        "best_kl": 1.7999999523162842,
        "best_std": 0.233819842338562,
        "cur_kl": 2.598749876022339,
        "cur_std": 0.2854604721069336,
        "orig_prompt": {
            "text": "The day before two days after the day before tomorrow is Saturday. What day is it today?",
            "ids": [
                510,
                1388,
                1078,
                767,
                1897,
                846,
                253,
                1388,
                1078,
                10873,
                310,
                7814,
                15,
                1737,
                1388,
                310,
                352,
                3063,
                32
            ],
            "prompt_start_slice": 0,
            "prompt_end_slice": 19,
            "doc_start_slice": 19,
            "doc_end_slice": 51
        },
        "optim_prompt": {
            "text": "officbic fact day two days after the day before tomorrow is Saturday. Can you tell, what day is today?",
            "ids": [
                19102,
                46372,
                958,
                1388,
                767,
                1897,
                846,
                253,
                1388,
                1078,
                10873,
                310,
                7814,
                15,
                2615,
                368,
                2028,
                13,
                752,
                1388,
                310,
                3063,
                32
            ],
            "prompt_start_slice": 0,
            "prompt_end_slice": 23,
            "doc_start_slice": 23,
            "doc_end_slice": 55
        },
        "nll_prompt": -110.5
    },
    {
        "epoch": 32,
        "loss": 3.0199999809265137,
        "best_loss": 2.9887499809265137,
        "best_kl": 1.7999999523162842,
        "best_std": 0.233819842338562,
        "cur_kl": 2.7587499618530273,
        "cur_std": 0.27798118591308596,
        "orig_prompt": {
            "text": "The day before two days after the day before tomorrow is Saturday. What day is it today?",
            "ids": [
                510,
                1388,
                1078,
                767,
                1897,
                846,
                253,
                1388,
                1078,
                10873,
                310,
                7814,
                15,
                1737,
                1388,
                310,
                352,
                3063,
                32
            ],
            "prompt_start_slice": 0,
            "prompt_end_slice": 19,
            "doc_start_slice": 19,
            "doc_end_slice": 51
        },
        "optim_prompt": {
            "text": "officbicel day two days after the day before tomorrow is Saturday. Can you tell, what day is today?",
            "ids": [
                19102,
                46372,
                293,
                1388,
                767,
                1897,
                846,
                253,
                1388,
                1078,
                10873,
                310,
                7814,
                15,
                2615,
                368,
                2028,
                13,
                752,
                1388,
                310,
                3063,
                32
            ],
            "prompt_start_slice": 0,
            "prompt_end_slice": 23,
            "doc_start_slice": 23,
            "doc_end_slice": 55
        },
        "nll_prompt": -106.0
    },
    {
        "epoch": 33,
        "loss": 3.012500047683716,
        "best_loss": 2.9887499809265137,
        "best_kl": 1.7999999523162842,
        "best_std": 0.233819842338562,
        "cur_kl": 2.6287498474121094,
        "cur_std": 0.2913822174072266,
        "orig_prompt": {
            "text": "The day before two days after the day before tomorrow is Saturday. What day is it today?",
            "ids": [
                510,
                1388,
                1078,
                767,
                1897,
                846,
                253,
                1388,
                1078,
                10873,
                310,
                7814,
                15,
                1737,
                1388,
                310,
                352,
                3063,
                32
            ],
            "prompt_start_slice": 0,
            "prompt_end_slice": 19,
            "doc_start_slice": 19,
            "doc_end_slice": 51
        },
        "optim_prompt": {
            "text": "mysbicel day two days after the day before tomorrow is Saturday. Can you tell, what day is today?",
            "ids": [
                17089,
                46372,
                293,
                1388,
                767,
                1897,
                846,
                253,
                1388,
                1078,
                10873,
                310,
                7814,
                15,
                2615,
                368,
                2028,
                13,
                752,
                1388,
                310,
                3063,
                32
            ],
            "prompt_start_slice": 0,
            "prompt_end_slice": 23,
            "doc_start_slice": 23,
            "doc_end_slice": 55
        },
        "nll_prompt": -104.0
    },
    {
        "epoch": 34,
        "loss": 3.021250009536743,
        "best_loss": 2.9887499809265137,
        "best_kl": 1.7999999523162842,
        "best_std": 0.233819842338562,
        "cur_kl": 3.106250047683716,
        "cur_std": 0.2919931888580322,
        "orig_prompt": {
            "text": "The day before two days after the day before tomorrow is Saturday. What day is it today?",
            "ids": [
                510,
                1388,
                1078,
                767,
                1897,
                846,
                253,
                1388,
                1078,
                10873,
                310,
                7814,
                15,
                1737,
                1388,
                310,
                352,
                3063,
                32
            ],
            "prompt_start_slice": 0,
            "prompt_end_slice": 19,
            "doc_start_slice": 19,
            "doc_end_slice": 51
        },
        "optim_prompt": {
            "text": "mysbic waiting day two days after the day before tomorrow is Saturday. Can you tell, what day is today?",
            "ids": [
                17089,
                46372,
                6179,
                1388,
                767,
                1897,
                846,
                253,
                1388,
                1078,
                10873,
                310,
                7814,
                15,
                2615,
                368,
                2028,
                13,
                752,
                1388,
                310,
                3063,
                32
            ],
            "prompt_start_slice": 0,
            "prompt_end_slice": 23,
            "doc_start_slice": 23,
            "doc_end_slice": 55
        },
        "nll_prompt": -106.0
    },
    {
        "epoch": 35,
        "loss": 3.016249895095825,
        "best_loss": 2.9887499809265137,
        "best_kl": 1.7999999523162842,
        "best_std": 0.233819842338562,
        "cur_kl": 2.6862499713897705,
        "cur_std": 0.2814189910888672,
        "orig_prompt": {
            "text": "The day before two days after the day before tomorrow is Saturday. What day is it today?",
            "ids": [
                510,
                1388,
                1078,
                767,
                1897,
                846,
                253,
                1388,
                1078,
                10873,
                310,
                7814,
                15,
                1737,
                1388,
                310,
                352,
                3063,
                32
            ],
            "prompt_start_slice": 0,
            "prompt_end_slice": 19,
            "doc_start_slice": 19,
            "doc_end_slice": 51
        },
        "optim_prompt": {
            "text": "mys seated waiting day two days after the day before tomorrow is Saturday. Can you tell, what day is today?",
            "ids": [
                17089,
                22813,
                6179,
                1388,
                767,
                1897,
                846,
                253,
                1388,
                1078,
                10873,
                310,
                7814,
                15,
                2615,
                368,
                2028,
                13,
                752,
                1388,
                310,
                3063,
                32
            ],
            "prompt_start_slice": 0,
            "prompt_end_slice": 23,
            "doc_start_slice": 23,
            "doc_end_slice": 55
        },
        "nll_prompt": -103.5
    },
    {
        "epoch": 36,
        "loss": 3.012500047683716,
        "best_loss": 2.9887499809265137,
        "best_kl": 1.7999999523162842,
        "best_std": 0.233819842338562,
        "cur_kl": 2.706249952316284,
        "cur_std": 0.28724119663238523,
        "orig_prompt": {
            "text": "The day before two days after the day before tomorrow is Saturday. What day is it today?",
            "ids": [
                510,
                1388,
                1078,
                767,
                1897,
                846,
                253,
                1388,
                1078,
                10873,
                310,
                7814,
                15,
                1737,
                1388,
                310,
                352,
                3063,
                32
            ],
            "prompt_start_slice": 0,
            "prompt_end_slice": 19,
            "doc_start_slice": 19,
            "doc_end_slice": 51
        },
        "optim_prompt": {
            "text": "mys seated authority day two days after the day before tomorrow is Saturday. Can you tell, what day is today?",
            "ids": [
                17089,
                22813,
                6265,
                1388,
                767,
                1897,
                846,
                253,
                1388,
                1078,
                10873,
                310,
                7814,
                15,
                2615,
                368,
                2028,
                13,
                752,
                1388,
                310,
                3063,
                32
            ],
            "prompt_start_slice": 0,
            "prompt_end_slice": 23,
            "doc_start_slice": 23,
            "doc_end_slice": 55
        },
        "nll_prompt": -106.5
    },
    {
        "epoch": 37,
        "loss": 3.012500047683716,
        "best_loss": 2.9887499809265137,
        "best_kl": 1.7999999523162842,
        "best_std": 0.233819842338562,
        "cur_kl": 2.65625,
        "cur_std": 0.2788435220718384,
        "orig_prompt": {
            "text": "The day before two days after the day before tomorrow is Saturday. What day is it today?",
            "ids": [
                510,
                1388,
                1078,
                767,
                1897,
                846,
                253,
                1388,
                1078,
                10873,
                310,
                7814,
                15,
                1737,
                1388,
                310,
                352,
                3063,
                32
            ],
            "prompt_start_slice": 0,
            "prompt_end_slice": 19,
            "doc_start_slice": 19,
            "doc_end_slice": 51
        },
        "optim_prompt": {
            "text": "mys seated intoxicated day two days after the day before tomorrow is Saturday. Can you tell, what day is today?",
            "ids": [
                17089,
                22813,
                45192,
                1388,
                767,
                1897,
                846,
                253,
                1388,
                1078,
                10873,
                310,
                7814,
                15,
                2615,
                368,
                2028,
                13,
                752,
                1388,
                310,
                3063,
                32
            ],
            "prompt_start_slice": 0,
            "prompt_end_slice": 23,
            "doc_start_slice": 23,
            "doc_end_slice": 55
        },
        "nll_prompt": -110.0
    },
    {
        "epoch": 38,
        "loss": 3.009999990463257,
        "best_loss": 2.9887499809265137,
        "best_kl": 1.7999999523162842,
        "best_std": 0.233819842338562,
        "cur_kl": 2.4912500381469727,
        "cur_std": 0.28915724754333494,
        "orig_prompt": {
            "text": "The day before two days after the day before tomorrow is Saturday. What day is it today?",
            "ids": [
                510,
                1388,
                1078,
                767,
                1897,
                846,
                253,
                1388,
                1078,
                10873,
                310,
                7814,
                15,
                1737,
                1388,
                310,
                352,
                3063,
                32
            ],
            "prompt_start_slice": 0,
            "prompt_end_slice": 19,
            "doc_start_slice": 19,
            "doc_end_slice": 51
        },
        "optim_prompt": {
            "text": "mys seated intoxicated and two days after the day before tomorrow is Saturday. Can you tell, what day is today?",
            "ids": [
                17089,
                22813,
                45192,
                285,
                767,
                1897,
                846,
                253,
                1388,
                1078,
                10873,
                310,
                7814,
                15,
                2615,
                368,
                2028,
                13,
                752,
                1388,
                310,
                3063,
                32
            ],
            "prompt_start_slice": 0,
            "prompt_end_slice": 23,
            "doc_start_slice": 23,
            "doc_end_slice": 55
        },
        "nll_prompt": -104.5
    },
    {
        "epoch": 39,
        "loss": 3.016249895095825,
        "best_loss": 2.9887499809265137,
        "best_kl": 1.7999999523162842,
        "best_std": 0.233819842338562,
        "cur_kl": 2.7337498664855957,
        "cur_std": 0.3043023347854614,
        "orig_prompt": {
            "text": "The day before two days after the day before tomorrow is Saturday. What day is it today?",
            "ids": [
                510,
                1388,
                1078,
                767,
                1897,
                846,
                253,
                1388,
                1078,
                10873,
                310,
                7814,
                15,
                1737,
                1388,
                310,
                352,
                3063,
                32
            ],
            "prompt_start_slice": 0,
            "prompt_end_slice": 19,
            "doc_start_slice": 19,
            "doc_end_slice": 51
        },
        "optim_prompt": {
            "text": "mys seated intoxicated and two days after the day before next is Saturday. Can you tell, what day is today?",
            "ids": [
                17089,
                22813,
                45192,
                285,
                767,
                1897,
                846,
                253,
                1388,
                1078,
                1735,
                310,
                7814,
                15,
                2615,
                368,
                2028,
                13,
                752,
                1388,
                310,
                3063,
                32
            ],
            "prompt_start_slice": 0,
            "prompt_end_slice": 23,
            "doc_start_slice": 23,
            "doc_end_slice": 55
        },
        "nll_prompt": -112.0
    },
    {
        "epoch": 40,
        "loss": 3.0225000381469727,
        "best_loss": 2.9887499809265137,
        "best_kl": 1.7999999523162842,
        "best_std": 0.233819842338562,
        "cur_kl": 2.9412498474121094,
        "cur_std": 0.2946891784667969,
        "orig_prompt": {
            "text": "The day before two days after the day before tomorrow is Saturday. What day is it today?",
            "ids": [
                510,
                1388,
                1078,
                767,
                1897,
                846,
                253,
                1388,
                1078,
                10873,
                310,
                7814,
                15,
                1737,
                1388,
                310,
                352,
                3063,
                32
            ],
            "prompt_start_slice": 0,
            "prompt_end_slice": 19,
            "doc_start_slice": 19,
            "doc_end_slice": 51
        },
        "optim_prompt": {
            "text": " eighty seated intoxicated and two days after the day before next is Saturday. Can you tell, what day is today?",
            "ids": [
                32571,
                22813,
                45192,
                285,
                767,
                1897,
                846,
                253,
                1388,
                1078,
                1735,
                310,
                7814,
                15,
                2615,
                368,
                2028,
                13,
                752,
                1388,
                310,
                3063,
                32
            ],
            "prompt_start_slice": 0,
            "prompt_end_slice": 23,
            "doc_start_slice": 23,
            "doc_end_slice": 55
        },
        "nll_prompt": -109.5
    },
    {
        "epoch": 41,
        "loss": 3.0249998569488525,
        "best_loss": 2.9887499809265137,
        "best_kl": 1.7999999523162842,
        "best_std": 0.233819842338562,
        "cur_kl": 2.976249933242798,
        "cur_std": 0.3012007474899292,
        "orig_prompt": {
            "text": "The day before two days after the day before tomorrow is Saturday. What day is it today?",
            "ids": [
                510,
                1388,
                1078,
                767,
                1897,
                846,
                253,
                1388,
                1078,
                10873,
                310,
                7814,
                15,
                1737,
                1388,
                310,
                352,
                3063,
                32
            ],
            "prompt_start_slice": 0,
            "prompt_end_slice": 19,
            "doc_start_slice": 19,
            "doc_end_slice": 51
        },
        "optim_prompt": {
            "text": "am seated intoxicated and two days after the day before next is Saturday. Can you tell, what day is today?",
            "ids": [
                312,
                22813,
                45192,
                285,
                767,
                1897,
                846,
                253,
                1388,
                1078,
                1735,
                310,
                7814,
                15,
                2615,
                368,
                2028,
                13,
                752,
                1388,
                310,
                3063,
                32
            ],
            "prompt_start_slice": 0,
            "prompt_end_slice": 23,
            "doc_start_slice": 23,
            "doc_end_slice": 55
        },
        "nll_prompt": -111.5
    },
    {
        "epoch": 42,
        "loss": 3.012500047683716,
        "best_loss": 2.9887499809265137,
        "best_kl": 1.7999999523162842,
        "best_std": 0.233819842338562,
        "cur_kl": 2.6875,
        "cur_std": 0.28128437995910643,
        "orig_prompt": {
            "text": "The day before two days after the day before tomorrow is Saturday. What day is it today?",
            "ids": [
                510,
                1388,
                1078,
                767,
                1897,
                846,
                253,
                1388,
                1078,
                10873,
                310,
                7814,
                15,
                1737,
                1388,
                310,
                352,
                3063,
                32
            ],
            "prompt_start_slice": 0,
            "prompt_end_slice": 19,
            "doc_start_slice": 19,
            "doc_end_slice": 51
        },
        "optim_prompt": {
            "text": "am seated intoxicated and two days after the day before tomorrow is Saturday. Can you tell, what day is today?",
            "ids": [
                312,
                22813,
                45192,
                285,
                767,
                1897,
                846,
                253,
                1388,
                1078,
                10873,
                310,
                7814,
                15,
                2615,
                368,
                2028,
                13,
                752,
                1388,
                310,
                3063,
                32
            ],
            "prompt_start_slice": 0,
            "prompt_end_slice": 23,
            "doc_start_slice": 23,
            "doc_end_slice": 55
        },
        "nll_prompt": -105.0
    },
    {
        "epoch": 43,
        "loss": 3.016249895095825,
        "best_loss": 2.9887499809265137,
        "best_kl": 1.7999999523162842,
        "best_std": 0.233819842338562,
        "cur_kl": 2.728749990463257,
        "cur_std": 0.2870140552520752,
        "orig_prompt": {
            "text": "The day before two days after the day before tomorrow is Saturday. What day is it today?",
            "ids": [
                510,
                1388,
                1078,
                767,
                1897,
                846,
                253,
                1388,
                1078,
                10873,
                310,
                7814,
                15,
                1737,
                1388,
                310,
                352,
                3063,
                32
            ],
            "prompt_start_slice": 0,
            "prompt_end_slice": 19,
            "doc_start_slice": 19,
            "doc_end_slice": 51
        },
        "optim_prompt": {
            "text": "am seated intoxicated continues two days after the day before tomorrow is Saturday. Can you tell, what day is today?",
            "ids": [
                312,
                22813,
                45192,
                7788,
                767,
                1897,
                846,
                253,
                1388,
                1078,
                10873,
                310,
                7814,
                15,
                2615,
                368,
                2028,
                13,
                752,
                1388,
                310,
                3063,
                32
            ],
            "prompt_start_slice": 0,
            "prompt_end_slice": 23,
            "doc_start_slice": 23,
            "doc_end_slice": 55
        },
        "nll_prompt": -110.0
    },
    {
        "epoch": 44,
        "loss": 3.0199999809265137,
        "best_loss": 2.9887499809265137,
        "best_kl": 1.7999999523162842,
        "best_std": 0.233819842338562,
        "cur_kl": 2.841249942779541,
        "cur_std": 0.3188513994216919,
        "orig_prompt": {
            "text": "The day before two days after the day before tomorrow is Saturday. What day is it today?",
            "ids": [
                510,
                1388,
                1078,
                767,
                1897,
                846,
                253,
                1388,
                1078,
                10873,
                310,
                7814,
                15,
                1737,
                1388,
                310,
                352,
                3063,
                32
            ],
            "prompt_start_slice": 0,
            "prompt_end_slice": 19,
            "doc_start_slice": 19,
            "doc_end_slice": 51
        },
        "optim_prompt": {
            "text": "reduction seated intoxicated continues two days after the day before tomorrow is Saturday. Can you tell, what day is today?",
            "ids": [
                44571,
                22813,
                45192,
                7788,
                767,
                1897,
                846,
                253,
                1388,
                1078,
                10873,
                310,
                7814,
                15,
                2615,
                368,
                2028,
                13,
                752,
                1388,
                310,
                3063,
                32
            ],
            "prompt_start_slice": 0,
            "prompt_end_slice": 23,
            "doc_start_slice": 23,
            "doc_end_slice": 55
        },
        "nll_prompt": -114.0
    },
    {
        "epoch": 45,
        "loss": 3.0174999237060547,
        "best_loss": 2.9887499809265137,
        "best_kl": 1.7999999523162842,
        "best_std": 0.233819842338562,
        "cur_kl": 2.8837499618530273,
        "cur_std": 0.3070368766784668,
        "orig_prompt": {
            "text": "The day before two days after the day before tomorrow is Saturday. What day is it today?",
            "ids": [
                510,
                1388,
                1078,
                767,
                1897,
                846,
                253,
                1388,
                1078,
                10873,
                310,
                7814,
                15,
                1737,
                1388,
                310,
                352,
                3063,
                32
            ],
            "prompt_start_slice": 0,
            "prompt_end_slice": 19,
            "doc_start_slice": 19,
            "doc_end_slice": 51
        },
        "optim_prompt": {
            "text": "IM seated intoxicated continues two days after the day before tomorrow is Saturday. Can you tell, what day is today?",
            "ids": [
                2894,
                22813,
                45192,
                7788,
                767,
                1897,
                846,
                253,
                1388,
                1078,
                10873,
                310,
                7814,
                15,
                2615,
                368,
                2028,
                13,
                752,
                1388,
                310,
                3063,
                32
            ],
            "prompt_start_slice": 0,
            "prompt_end_slice": 23,
            "doc_start_slice": 23,
            "doc_end_slice": 55
        },
        "nll_prompt": -113.5
    },
    {
        "epoch": 46,
        "loss": 3.0149998664855957,
        "best_loss": 2.9887499809265137,
        "best_kl": 1.7999999523162842,
        "best_std": 0.233819842338562,
        "cur_kl": 2.776249885559082,
        "cur_std": 0.29553866386413574,
        "orig_prompt": {
            "text": "The day before two days after the day before tomorrow is Saturday. What day is it today?",
            "ids": [
                510,
                1388,
                1078,
                767,
                1897,
                846,
                253,
                1388,
                1078,
                10873,
                310,
                7814,
                15,
                1737,
                1388,
                310,
                352,
                3063,
                32
            ],
            "prompt_start_slice": 0,
            "prompt_end_slice": 19,
            "doc_start_slice": 19,
            "doc_end_slice": 51
        },
        "optim_prompt": {
            "text": "IM seated find continues two days after the day before tomorrow is Saturday. Can you tell, what day is today?",
            "ids": [
                2894,
                22813,
                1089,
                7788,
                767,
                1897,
                846,
                253,
                1388,
                1078,
                10873,
                310,
                7814,
                15,
                2615,
                368,
                2028,
                13,
                752,
                1388,
                310,
                3063,
                32
            ],
            "prompt_start_slice": 0,
            "prompt_end_slice": 23,
            "doc_start_slice": 23,
            "doc_end_slice": 55
        },
        "nll_prompt": -106.0
    },
    {
        "epoch": 47,
        "loss": 3.028749942779541,
        "best_loss": 2.9887499809265137,
        "best_kl": 1.7999999523162842,
        "best_std": 0.233819842338562,
        "cur_kl": 2.9862499237060547,
        "cur_std": 0.29987316131591796,
        "orig_prompt": {
            "text": "The day before two days after the day before tomorrow is Saturday. What day is it today?",
            "ids": [
                510,
                1388,
                1078,
                767,
                1897,
                846,
                253,
                1388,
                1078,
                10873,
                310,
                7814,
                15,
                1737,
                1388,
                310,
                352,
                3063,
                32
            ],
            "prompt_start_slice": 0,
            "prompt_end_slice": 19,
            "doc_start_slice": 19,
            "doc_end_slice": 51
        },
        "optim_prompt": {
            "text": " 222 seated find continues two days after the day before tomorrow is Saturday. Can you tell, what day is today?",
            "ids": [
                25653,
                22813,
                1089,
                7788,
                767,
                1897,
                846,
                253,
                1388,
                1078,
                10873,
                310,
                7814,
                15,
                2615,
                368,
                2028,
                13,
                752,
                1388,
                310,
                3063,
                32
            ],
            "prompt_start_slice": 0,
            "prompt_end_slice": 23,
            "doc_start_slice": 23,
            "doc_end_slice": 55
        },
        "nll_prompt": -110.0
    },
    {
        "epoch": 48,
        "loss": 3.009999990463257,
        "best_loss": 2.9887499809265137,
        "best_kl": 1.7999999523162842,
        "best_std": 0.233819842338562,
        "cur_kl": 2.65625,
        "cur_std": 0.2984724283218384,
        "orig_prompt": {
            "text": "The day before two days after the day before tomorrow is Saturday. What day is it today?",
            "ids": [
                510,
                1388,
                1078,
                767,
                1897,
                846,
                253,
                1388,
                1078,
                10873,
                310,
                7814,
                15,
                1737,
                1388,
                310,
                352,
                3063,
                32
            ],
            "prompt_start_slice": 0,
            "prompt_end_slice": 19,
            "doc_start_slice": 19,
            "doc_end_slice": 51
        },
        "optim_prompt": {
            "text": "minor seated find continues two days after the day before tomorrow is Saturday. Can you tell, what day is today?",
            "ids": [
                37585,
                22813,
                1089,
                7788,
                767,
                1897,
                846,
                253,
                1388,
                1078,
                10873,
                310,
                7814,
                15,
                2615,
                368,
                2028,
                13,
                752,
                1388,
                310,
                3063,
                32
            ],
            "prompt_start_slice": 0,
            "prompt_end_slice": 23,
            "doc_start_slice": 23,
            "doc_end_slice": 55
        },
        "nll_prompt": -105.5
    },
    {
        "epoch": 49,
        "loss": 3.026249885559082,
        "best_loss": 2.9887499809265137,
        "best_kl": 1.7999999523162842,
        "best_std": 0.233819842338562,
        "cur_kl": 3.021250009536743,
        "cur_std": 0.3049520492553711,
        "orig_prompt": {
            "text": "The day before two days after the day before tomorrow is Saturday. What day is it today?",
            "ids": [
                510,
                1388,
                1078,
                767,
                1897,
                846,
                253,
                1388,
                1078,
                10873,
                310,
                7814,
                15,
                1737,
                1388,
                310,
                352,
                3063,
                32
            ],
            "prompt_start_slice": 0,
            "prompt_end_slice": 19,
            "doc_start_slice": 19,
            "doc_end_slice": 51
        },
        "optim_prompt": {
            "text": "Help seated find continues two days after the day before tomorrow is Saturday. Can you tell, what day is today?",
            "ids": [
                19576,
                22813,
                1089,
                7788,
                767,
                1897,
                846,
                253,
                1388,
                1078,
                10873,
                310,
                7814,
                15,
                2615,
                368,
                2028,
                13,
                752,
                1388,
                310,
                3063,
                32
            ],
            "prompt_start_slice": 0,
            "prompt_end_slice": 23,
            "doc_start_slice": 23,
            "doc_end_slice": 55
        },
        "nll_prompt": -103.5
    },
    {
        "epoch": 50,
        "loss": 3.0225000381469727,
        "best_loss": 2.9887499809265137,
        "best_kl": 1.7999999523162842,
        "best_std": 0.233819842338562,
        "cur_kl": 2.918750047683716,
        "cur_std": 0.3043631315231323,
        "orig_prompt": {
            "text": "The day before two days after the day before tomorrow is Saturday. What day is it today?",
            "ids": [
                510,
                1388,
                1078,
                767,
                1897,
                846,
                253,
                1388,
                1078,
                10873,
                310,
                7814,
                15,
                1737,
                1388,
                310,
                352,
                3063,
                32
            ],
            "prompt_start_slice": 0,
            "prompt_end_slice": 19,
            "doc_start_slice": 19,
            "doc_end_slice": 51
        },
        "optim_prompt": {
            "text": "Evidence seated find continues two days after the day before tomorrow is Saturday. Can you tell, what day is today?",
            "ids": [
                49153,
                22813,
                1089,
                7788,
                767,
                1897,
                846,
                253,
                1388,
                1078,
                10873,
                310,
                7814,
                15,
                2615,
                368,
                2028,
                13,
                752,
                1388,
                310,
                3063,
                32
            ],
            "prompt_start_slice": 0,
            "prompt_end_slice": 23,
            "doc_start_slice": 23,
            "doc_end_slice": 55
        },
        "nll_prompt": -108.0
    }
]